[{"id":4,"action_name":"safe_route_action","source_zone":"middleverse","target_zone":"marketplace","route_type":"commerce_route","action_status":"routed","created_at":"2026-04-01 01:03:58"},
{"id":3,"action_name":"open_service_dispatch","source_zone":"middleverse","target_zone":"dispatch","route_type":"service_route","action_status":"routed","created_at":"2026-04-01 01:03:41"},
{"id":2,"action_name":"launch_creator_room","source_zone":"middleverse","target_zone":"creator_tv","route_type":"creator_route","action_status":"routed","created_at":"2026-04-01 01:03:41"},
{"id":1,"action_name":"open_holo_store","source_zone":"middleverse","target_zone":"marketplace","route_type":"commerce_route","action_status":"routed","created_at":"2026-04-01 01:03:41"}]
